{
    "Neutral" : {
        "size" : [500, 70],
        "fullScreen" : "false",
        "bgColor" : [255, 0, 0, 255],
        "bgImage" : "",
        "bgImgColor" : [255, 0, 0, 255],
        "textColor" : [255, 0, 0, 255],
        "textFont" : "Main",
        "textPadding" : [300, 0],
        "textSize" : 50,
        "textOriginCenter" : "false",
        "glyph" : "",
        "glyphPadding" : [150, 16]
    },
    "Player" : {
        "size" : [500, 70],
        "fullScreen" : "false",
        "bgColor" : [0, 255, 174, 255],
        "bgImage" : "",
        "bgImgColor" : [0, 255, 0, 255],
        "textColor" : [0, 255, 174, 255],
        "textFont" : "Main",
        "textPadding" : [300, 0],
        "textSize" : 50,
        "textOriginCenter" : "false",
        "glyph" : "",
        "glyphPadding" : [150, 16]
    }
}